atinycron/__init__.py
atinycron-0.0.1.dev7.dist-info/licenses/LICENSE
atinycron-0.0.1.dev7.dist-info/METADATA
atinycron-0.0.1.dev7.dist-info/WHEEL
atinycron-0.0.1.dev7.dist-info/top_level.txt
atinycron-0.0.1.dev7.dist-info/RECORD
