Metadata-Version: 2.4
Name: atinycron
Version: 0.0.1.dev7
Summary: Async Tiny Cron
Author-email: "M@gicAgCl(DEAD)" <wyqsmith@aegeanstudio.com>
Requires-Python: >=3.12
License-File: LICENSE
Dynamic: license-file
